package_fraction/__init__.py
package_fraction-0.0.1.dist-info/Licence.txt
package_fraction-0.0.1.dist-info/METADATA
package_fraction-0.0.1.dist-info/WHEEL
package_fraction-0.0.1.dist-info/top_level.txt
package_fraction-0.0.1.dist-info/RECORD
